README.md
setup.cfg
setup.py
loggerj/__init__.py
loggerj/log.py
loggerj/logger.py
loggerj.egg-info/PKG-INFO
loggerj.egg-info/SOURCES.txt
loggerj.egg-info/dependency_links.txt
loggerj.egg-info/not-zip-safe
loggerj.egg-info/top_level.txt