Metadata-Version: 1.0
Name: loggerj
Version: 1.0
Summary: Module to facilitate the creation of logs with logging
Home-page: https://github.com/Jallyssonmr/loggerj
Author: Jallysson M. Rocha
Author-email: jallysson_miranda@outlook.com
License: MIT
Keywords: log,logging,logger,python
Platform: UNKNOWN
